README.md
setup.cfg
setup.py
modern_logic_client/__init__.py
modern_logic_client/api_client.py
modern_logic_client/configuration.py
modern_logic_client/rest.py
modern_logic_client.egg-info/PKG-INFO
modern_logic_client.egg-info/SOURCES.txt
modern_logic_client.egg-info/dependency_links.txt
modern_logic_client.egg-info/requires.txt
modern_logic_client.egg-info/top_level.txt
modern_logic_client/api/__init__.py
modern_logic_client/api/alerts_api.py
modern_logic_client/api/customers_api.py
modern_logic_client/api/data_sources_api.py
modern_logic_client/api/executions_api.py
modern_logic_client/api/webhooks_api.py
modern_logic_client/api/workflows_api.py
modern_logic_client/models/__init__.py
modern_logic_client/models/alert.py
modern_logic_client/models/alert_item.py
modern_logic_client/models/customer.py
modern_logic_client/models/customer_item.py
modern_logic_client/models/data_source.py
modern_logic_client/models/data_source_call.py
modern_logic_client/models/data_source_call_item.py
modern_logic_client/models/data_source_type.py
modern_logic_client/models/execution.py
modern_logic_client/models/execution_input.py
modern_logic_client/models/execution_item.py
modern_logic_client/models/inline_response200.py
modern_logic_client/models/inline_response2001.py
modern_logic_client/models/inline_response2002.py
modern_logic_client/models/inline_response2003.py
modern_logic_client/models/inline_response2004.py
modern_logic_client/models/inline_response2005.py
modern_logic_client/models/inline_response2006.py
modern_logic_client/models/inline_response2007.py
modern_logic_client/models/inline_response2008.py
modern_logic_client/models/list_response.py
modern_logic_client/models/rule_set_warning.py
modern_logic_client/models/rule_warning.py
modern_logic_client/models/webhook.py
modern_logic_client/models/webhook_response.py
modern_logic_client/models/workflow.py
modern_logic_client/models/workflow_execution_result.py
modern_logic_client/models/workflow_version.py
test/__init__.py
test/test_alert.py
test/test_alert_item.py
test/test_alerts_api.py
test/test_customer.py
test/test_customer_item.py
test/test_customers_api.py
test/test_data_source.py
test/test_data_source_call.py
