Metadata-Version: 1.1
Name: modern-logic-client
Version: 1.0.0
Summary: Modern Logic Api
Home-page: https://github.com/latourette359/modern_logic_client
Author: UNKNOWN
Author-email: info@usemodernlogic.com
License: MIT
Download-URL: https://github.com/latourette359/modern_logic_client/archive/refs/tags/1.0.0.tar.gz
Keywords: Swagger,Modern Logic Api
Platform: UNKNOWN
